{
  "title": "Vision conveyor camera and lighting",
  "file": "Vision_conveyor_camera_and_lighting",
  "section": "Program",
  "type": "reference",
  "syntax": "",
  "parameters": "",
  "description": "Vision conveyor camera and lighting\n\nVision conveyor camera and lighting\n\nIt is important to choose the correct camera and lighting for the vision conveyors used in your application.\n\nFor applications with a slow moving conveyor and non-critical pick up constraints, you may be able to use a Vision Guide camera and simple lighting with no strobe.\n\nFor applications with fast moving parts, you will need to use a camera that is capable of asynchronous reset along with a strobe lamp.  This method is more expensive.",
  "notes": "",
  "see_also": "",
  "examples": []
}