{
  "code": 513,
  "title": "Write to import all system data",
  "protocol": "Modbus",
  "category": "Controller",
  "description": "Use function code #513 to import all system data , including contents of parameters, sequence s, sources, controller, and tool.",
  "request_fields": [
    {
      "register": "C8",
      "field": "Function code",
      "description": "513"
    },
    {
      "register": "C9",
      "field": "Version number",
      "description": "0"
    },
    {
      "register": "CA",
      "field": "Read d ata from 0: USB Disk",
      "description": ""
    },
    {
      "register": "CB to CD",
      "field": "Reserved",
      "description": "-"
    },
    {
      "register": "CE",
      "field": "Request to send command",
      "description": "1 (to be filled in last )"
    }
  ],
  "return_fields": [
    {
      "register": "CF",
      "field": "Function code",
      "description": "513"
    },
    {
      "register": "D0",
      "field": "Status",
      "description": "1: OK; 2: NOK"
    },
    {
      "register": "D1",
      "field": "Error code",
      "description": "-"
    }
  ],
  "error_codes": {},
  "notes": ""
}