{
  "code": 702,
  "title": "Clear the production report files",
  "protocol": "Modbus",
  "category": "Reports",
  "description": "Use function code #702 to delete all the production report files exported to the HMI .",
  "request_fields": [
    {
      "register": "C8",
      "field": "Function code",
      "description": "702"
    },
    {
      "register": "C9",
      "field": "Version number",
      "description": "0"
    },
    {
      "register": "CA",
      "field": "Confirm command",
      "description": "99"
    },
    {
      "register": "CB to CD",
      "field": "Reserved",
      "description": "-"
    },
    {
      "register": "CE",
      "field": "Request to send command",
      "description": "1 (to be filled in last )"
    }
  ],
  "return_fields": [
    {
      "register": "CF",
      "field": "Function code",
      "description": "702"
    },
    {
      "register": "D0",
      "field": "Status",
      "description": "1: OK; 2: NOK"
    },
    {
      "register": "D1",
      "field": "Error code",
      "description": "-"
    }
  ],
  "error_codes": {},
  "notes": ""
}