{
  "title": "LineFinder Results",
  "file": "LineFinder_Results",
  "section": "Program",
  "type": "reference",
  "syntax": "",
  "parameters": "",
  "description": "LineFinder Results\n\nLineFinder Results\n\nThe following list is a summary of the Edge object results with brief descriptions.  The details for each result are explained in the Vision Guide 8.0 Properties and Results Reference Manual.\n\nResults\tDescription\n\nAngle\tReturns the\n\t\t detection edge angle in the image coordinate system.\n\nCameraX1\tReturns the\n\t\t X coordinate for the start point of the detected edge line in\n\t\t the camera coordinate system.\n\nCameraY1\tReturns the\n\t\t Y coordinate for the start point of the detected edge line in\n\t\t the camera coordinate system.\n\nCameraX2\tReturns the\n\t\t X coordinate for the end point of the detected edge line in the\n\t\t camera coordinate system.\n\nCameraY2\tReturns the\n\t\t Y coordinate for the end point of the detected edge line in the\n\t\t camera coordinate system.\n\nClearanceOK\tReturns the\n\t\t result of decision for a clearance.\n\nContrast\tReturns the\n\t\t average contrast of the detected edges.\n\nEdgeCameraXYU\tReturns the\n\t\t CameraX, CameraY and Angle position coordinates of the edges found\n\t\t during the search. Runtime only.\n\nEdgePixelXYU\tReturns the\n\t\t PixelX, PixelY and Angle position coordinates of the edges found\n\t\t during the search. Runtime only.\n\nEdgeRobotXYU\tReturns the\n\t\t RobotX, RobotY and Angle position coordinates of the edges found\n\t\t during the search. Runtime only.\n\nFitError\tReturns the\n\t\t distance between each edge point and the rectangle detected as\n\t\t the root mean square (RMS).\n\nFound\tReturns whether\n\t\t the object was found. (i.e.  did the feature or part you\n\t\t are looking at have a shape score that is above the Accept property's\n\t\t current setting.)\n\nPassed\tReturns whether\n\t\t the object detection result was accepted.\n\nPixelLine\tRuntime only.\n\nReturns the\n\t\t four line coordinates X1, Y1, X2, Y2 in pixels.\n\nLength\tReturns the\n\t\t length of the detected edge line in millimeters.\n\nNumberFound\tReturns an\n\t\t object found.\n\n(The detected\n\t\t number can be from 0 up to the number set with the NumberToFind\n\t\t property.)\n\nPixelLength\tReturns the\n\t\t length of the detected edge line in pixels.\n\nPixelX1\tReturns the\n\t\t X coordinate position of the start point of the detected edge\n\t\t line in the image coordinate system.\n\nPixelY1\tReturns the\n\t\t Y coordinate position of the start point of the detected edge\n\t\t line in the image coordinate system.\n\nPixelX2\tReturns the\n\t\t X coordinate position of the end point of the detected edge line\n\t\t in the image coordinate system.\n\nPixelY2\tReturns the\n\t\t Y coordinate position of the end point of the detected edge line\n\t\t in the image coordinate system.\n\nRobotX1\tReturns the\n\t\t X coordinate position of the start point of the detected edge\n\t\t line in the Robot coordinate system.\n\nRobotY1\tReturns the\n\t\t Y coordinate position of the start point of the detected edge\n\t\t line in the Robot coordinate system.\n\nRobotX2\tReturns the\n\t\t X coordinate position of the end point of the detected edge line\n\t\t in the Robot coordinate system.\n\nRobotY2\tReturns the\n\t\t Y coordinate position of the end point of the detected edge line\n\t\t in the Robot coordinate system.\n\nShowAllResults\tDisplays a\n\t\t dialog which allows you to see all results for a specified vision\n\t\t object in a table form.  This makes it easy to compare results\n\t\t when the NumberToFind property is set to 0 or greater than 1.\n\nStrength\tReturns the\n\t\t average strength of the detected edges.\n\nTime\tReturns the\n\t\t amount of time required to process the object (unit: millisecond).",
  "notes": "",
  "see_also": "",
  "examples": []
}