{
  "title": "Step 4: Test the Blob Object and Examine the Results",
  "file": "Step4_TesttheBlobObjectandExaminetheResults",
  "section": "Program",
  "type": "reference",
  "syntax": "",
  "parameters": "",
  "description": "Step 4: Test the Blob Object and Examine the Results\n\nStep 4: Test the Blob Object and Examine the Results\n\nTo run the Blob object, click the [Run] button of the object on the execution panel. Results for the Blob object will now be displayed. The primary results to examine at this time are:\n\nFound result - Returns whether the blob was found. If the blob which was found does not meet the area constraints defined by the MinArea and MaxArea properties then the Found result will return as False.\n\nArea result - The area (in pixels) of the blob found.\n\nAngle result - The angle at which the Blob is oriented. This is computed from the angle of the minor axis and will be a value between +/- 90 degrees.\n\nTime result - The amount of time it took for the Blob object to execute.\n\nPixelX, PixelY - The XY position (in pixels) of the center of mass of the found blob.\n\nMinX, MinY, MaxX, MaxY - Combined these 4 values define the extrema of the blob. (A rectangle which is formed by touching the outermost points of the blob.)\n\nNote: The RobotXYU, RobotX, RobotY, Robot U and CameraX, CameraY, CameraXYU results will return [no cal] at this time. This means that no calibration was performed so it is impossible for the vision system to calculate the coordinate results with respect to the Robot World or Camera World. See Calibration for more information.",
  "notes": "",
  "see_also": "",
  "examples": []
}