{
  "title": "Inertia Page: Robot Manager Window",
  "file": "Inertia_Tab_Robot_Parameters",
  "section": "Operator",
  "type": "reference",
  "syntax": "",
  "parameters": "",
  "description": "Inertia Page: Robot Manager Window\n\n[Tools]-[Robot Manager]-[Inertia] Page\n\nThis page is for changing the Inertia parameters.\n\nFor more details on Inertia settings, refer to the following manual:\n\nSPEL+ Language Reference - Inertia Statement\n\nYou can also set by following \"Weight, Inertia, and Eccentricity/offset Measurement Utility\".\n\nThe following section describes the details.\n\nWeight, Inertia, and Eccentricity/offset Measurement Utility\n\nItem\tDescription\n\nLoad\n\t\t inertia\tType\n\t\t in the new load inertia of the payload on the robot in kgxm2.\n\t\t This includes the inertia of end effector plus the part to be\n\t\t carried.\n\nEccentricity\tType\n\t\t in the new eccentricity value in millimeters. This is the distance\n\t\t from rotational center of joint 4 to the center of gravity of\n\t\t end effector and part.\n\nApply\tSets\n\t\t the current values.\n\nRestore\tReverts\n\t\t to the previous values.\n\nDefaults\tDisplays\n\t\t factory default settings.",
  "notes": "",
  "see_also": "",
  "examples": []
}