{
  "title": "Specifications and precautions for Simulation (program execution on PC)",
  "file": "Simulator_PrecautionPC",
  "section": "Program",
  "type": "reference",
  "syntax": "",
  "parameters": "",
  "description": "Specifications and precautions for Simulation (program execution on PC)\n\nSpecifications and precautions for Simulation (program execution on PC)\n\nOverview\n\nThe Simulator produces the robot motions virtually on your PC.\n\nIt is designed to make the performance gap between the real system and the virtual system as small as possible.  However, a few differences in the virtual system are inevitable.  The operation time prediction and collision detection do not guarantee the precision.\n\nFully understand the contents in this chapter and check if the real system operates without any problems before you go to full-scale operation.\n\nOperation time prediction\n\nOperation time displayed in the [Robot Simulator] window is approximate time required for executing the program.\n\nTime for the motion commands such as Go, Jump reflects the Speed and Accel values in the program. The operation time may vary when you operate the real robots from the displayed operation time according to conditions such as the Fine setting and servo delay. In particular, when small ranges are used with the Fine instruction, the real robots need a longer operation time for accurate positioning.\n\nThe simulation cannot guarantee the precision but the margin of error in the operation time is within 10% when you execute motions with the standard cycle time (with the default Fine settings).\n\nConsidered\n\t\t in the operation time prediction\tNot considered\n\t\t in the operation time prediction\n\nRobot\n\t\t model\n\nSpeed settings\n\t\t (Speed, Speeds, etc.)\n\nAcceleration\n\t\t settings (Accel, Accels, etc.)\n\nLoad (Weight,\n\t\t Inertia)\n\nOthers (ARCH,\n\t\t CP)\tFine setting\n\n   Error\n\t\t within 10% from the default\n\n(Motions of standard cycle time)\n\n   With\n\t\t larger setting than the default, the operation time will be shorter.\n\n   With\n\t\t smaller setting than the default, the operation time will be shorter.\n\nServo delay\n\n   With\n\t\t the real robots, the operation will be longer.\n\nTime for the other commands than the motion commands is a virtually executed time on PC; therefore the actual time varies widely depending on the PC performance.\n\nWhen measuring the motion time between two points, as simple program as possible is recommended. Refer to Working with the user created system - 8. Measure the robot operation time.\n\nWhen measuring the motion time between two points, as simple program as possible is recommended. Refer to .\n\nCollision Detection Precision\n\nThe Simulator Collision Detection provides an indication whether robots collide with the peripheral equipment or not when the program is executed. It does not consider the error in path due to servo delay. Make sure to have a margin when you apply the simulation result for a real robot system.\n\nThe Simulator judges collisions more accurately when the robot motion speed is slow.\n\nThe judgment of collision detection during program execution is accomplished with the 3D display update. When your PC has high graphics performance, the collision judgment becomes more accurate.\n\nIn Playback mode, judgments on collision detections are made in all steps. This allows for more accurate detection.\n\nThe Simulator cannot guarantee the precision but the margin of error in the collision detection is within 10 mm when you execute motions with Speed 100% on a PC of the recommended specifications.\n\nMotion duty and Overload error\n\nIn the Simulator, you cannot detect overload errors. Even if the motion duty is excessively high and the robot should stop due overload error, it keeps operating.\n\nDuty 50% - As a measure of possible duty, the robot can really keep moving at duty 50% with the maximum acceleration/deceleration speed and without the overload error. However, it depends on the robot model type, load, points to go to, and acceleration/deceleration speed setting, etc.\n\nExecution on PC that does not meet recommended system requirements\n\nYou can install the Epson RC+ and use the Simulator functions on a PC that does not meet the recommended system requirements. However, it doesn't guarantee the correct motions because the following may happen:\n\nOperation\n\t time prediction is not accurate\n\nCollision\n\t Detection has a large margin of error\n\n3D\n\t display skips updates",
  "notes": "",
  "see_also": "",
  "examples": []
}