{
  "title": "Adding Standard Robots",
  "file": "Adding_Standard_Robots",
  "section": "Program",
  "type": "reference",
  "syntax": "",
  "parameters": "",
  "description": "Adding Standard Robots\n\nAdding a Standard Robot\n\nNOTE:  If you have purchased the PG motion system Option, you can add user defined robots. For details, refer to the following manual:\n\nRobot Controller Option PG Motion System\n\nIn\n\t the Epson RC+ 8.0 menu, select [Setup]-[System Configuration].\n\nSelect\n\t [Controller]-[Robots].\n\nClick the [Add]\n\t button. The dialog shown below appears.\n\nType in a name\n\t for the new manipulator and enter the serial number on the manipulator's\n\t nameplate. Any serial number can be used, but it is recommended that\n\t you use the number that is stamped on the manipulator.\n\nSelect a motion\n\t system to use from the [Motion System] dropdown list. If there are\n\t no other motion systems installed, then \"Standard\" will already be\n\t selected.\n\nSelect a Drive\n\t Unit for your manipulator from the [Drive Unit] dropdown list.\n\nSelect the robot\n\t type in the [Robot Family] box.\n\nSelect the series\n\t name of the manipulator in the [Series] box.\n\nSelect the robot\n\t model in the [Model] box.\n\n\tAvailable robots will be displayed according to the format of the currently\n\t installed motor driver. If you use [Dry run], all robots selected\n\t in step 8 will be shown.\n\nClick the [OK]\n\t button. The controller will be restarted.\n\nNOTE:  For the Controller with Safety Board, assign a robot using the safety function to Robot 1.",
  "notes": "",
  "see_also": "",
  "examples": []
}