{
  "title": "Arch VI",
  "file": "Arch_VI",
  "section": "Program",
  "type": "reference",
  "syntax": "",
  "parameters": "",
  "description": "Defines ARCH parameters (Z height to move before beginning horizontal motion) for use with the JUMP instructions.\n\nInputs\n\nSpel Ref\n\t\t In\tSpel reference from a previous Spel\n\t\t Ref Out.\n\nError In\tError condition from a previous Spel\n\t\t node.\n\nArch Number\tThe depart distance in millimeters moved\n\t\t at the beginning of the Jump instruction before starting horizontal\n\t\t motion.\n\nDepart Dist\tThe depart distance in millimeters moved\n\t\t at the beginning of the Jump instruction before starting horizontal\n\t\t motion.\n\nAppro Dist\tThe approach distance in millimeters\n\t\t above the target position of the Jump instruction.\n\nOutputs\n\nSpel Ref\n\t\t Out\tSpel reference output for next VI to\n\t\t use.\n\nError Out\tError condition output for subsequent\n\t\t Spel nodes.",
  "notes": "",
  "see_also": "Jump, Jump3\n\nArch Example",
  "examples": []
}