{
  "title": "Connecting and Disconnecting with Tasks Running",
  "file": "Connecting_and_Disconnecting_with_Tasks_Running",
  "section": "Program",
  "type": "reference",
  "syntax": "",
  "parameters": "",
  "description": "Connecting and Disconnecting with Tasks Running\n\nConnecting when Control Device is not PC\n\nConnecting while control device is not PC and tasks are not running\n\nIf your control device is not a PC and tasks are not running, you will see the following message box:\n\n[Leave the controller in Auto mode, I just want to monitor operation.]:\n\nSwitches to Monitor mode for monitoring the controller status.\n\n[Switch the controller to Program mode, I want to edit and debug programs.]:\n\nSwitches to Program mode for editing programs. The remote device cannot start programs until remote control has been enabled from the [Run] window.\n\nConnecting from a control device that is not a PC while tasks are running\n\nWhen using a control device that is not a PC and tasks are running, you can connect to a PC to the controller to monitor operation. For example, you can connect to a controller that is running tasks to temporarily monitor display output, tasks, and I/O, and then disconnect while tasks continue to run.\n\nIf the project on the PC is the same as on the controller, you will see the following message box when connection is established:\n\nIf the project on the PC is not the same as the project in the controller, you will see the following message box when connection is established:\n\nIf the [Leave the controller in Auto mode, I just want to monitor operation.] option is selected, the [Run] window will open if Epson RC+ 8.0 is started in Program mode. If Epson RC+ 8.0 is started in Operator mode, the [Operator Window] will appear. From the [Run] window or [Operator Window], you can view results of Print instructions. You can also use the Task Manager and I/O monitor.\n\nWhen monitoring controller operation, the controller remains in Auto mode. You cannot stop tasks from Epson RC+ 8.0, because the control device is not a PC. Stop the task from the current control device, and then connect the controller from Epson RC+ 8.0. Next, select Program mode to switch the controller to Program mode. (Refer to Connecting while control device is not PC and tasks are not running.)\n\nDisconnecting while tasks are running\n\nYou can only disconnect from the controller with tasks running when the control device is set to a device other than PC.\n\nStop\n\t communications with the controller by selecting [Offline] from the\n\t [Connection] dropdown list on the toolbar.\n\nYou may now disconnect the communications\n\t cable between the PC and the controller. Tasks will continue to run\n\t in the controller.",
  "notes": "",
  "see_also": "",
  "examples": []
}