{
  "title": "Step 1: Mount the camera",
  "file": "Step_1_Fixed_Mount_the_camera",
  "section": "Program",
  "type": "reference",
  "syntax": "",
  "parameters": "",
  "description": "Step 1: Mount the camera\n\nStandalone Steps\n\nStep 1: Mount the camera\n\n(1) Mount the camera at an angle of 40 to 90 degrees against the work plane.\n\nStep 2: Make a dot grid pattern (When performing distortion correction)\n\n(1) Create a dot grid pattern which has more than 100 points.  The grid pattern must cover the entire field of view with minimum distortion.  Accuracy of the grid pattern affects accuracy of image processing\n\nStep 3: Make a calibration plate\n\n(1) Make a plate with nine holes or targets that span the field of view of the camera.\n\nStep 4: Create vision sequence to find calibration reference targets\n\n(When performing distortion correction)\n\n(1) Create a sequence.\n\nRefer: Vision Sequence for Distortion Correction\n\nStep 5: Create vision sequence to find calibration reference targets\n\n(1) Create a vision sequence.\n\nRefer: Vision Sequences for Detecting Nine Targets\n\nStep 6: Create a calibration scheme\n\n(1) Click the [New Calibration] button on the Vision Guide toolbar.\n\n(2) The calibration wizard is run.\n\nSelect the name of calibration and a camera.  Select a source calibration for copying settings as necessary.\n\n(3) Select a standalone camera.\n\n(4) Configure the vision sequence for detecting the calibration reference targets.\n\n(5) Specify whether to enable distortion correction.\n\nIf distortion correction is enabled, select a vision sequence for detecting the dot grid pattern.\n\n(6) Configure the settings by following the steps to complete the wizard.\n\nStep 7: Setting for correction of lens distortion and camera installation distortion\n\n(1) Select the created calibration in the sequence or calibration tree.\n\n(2) Place the dot grid pattern on the work plane.\n\n(3) Select the Cal property below the DistCorrect property in the property list to execute detection of the dot grid pattern.\n\n(4) By selecting the calibration scheme created in Step 6 for the Calibration property (a sequence for positioning the calibration target), you can check the image which is corrected lens distortion and camera tilt.  Even when this setting is omitted, distortion will be corrected automatically when executing the calibration.\n\nStep 8: Calibration\n\n(1) Remove the dot grid pattern and place the calibration plate creates in Step 3.\n\n(2) Click the [Teach Points] button to set the coordinates for the nine targets in the calibration plate.\n\n(3) Click the [Calibrate] button to start the calibration cycle.  The calibration software positions the nine targets and then determines the calibration parameters after positioning the targets again to collect the statistic data.",
  "notes": "",
  "see_also": "",
  "examples": []
}