{
  "title": "The Epson RC+ 8.0 GUI",
  "file": "The_EPSON_RC+_GUI",
  "section": "Program",
  "type": "reference",
  "syntax": "",
  "parameters": "",
  "description": "The Epson RC+ 8.0 GUI\n\nThe Epson RC+ 8.0 GUI\n\nThe chapter contains information on the Epson RC+ 8.0 GUI.\n\nSummary\n\nSubwindows\n\nWindow layout\n\nTool Bar\n\nStatus Bar\n\nHelp\n\nFile Menu\n\nEdit Menu\n\nDisplay Menu\n\nProject\n\nRun\n\nTools\n\nSetup\n\nWindow\n\nHelp",
  "notes": "",
  "see_also": "",
  "examples": []
}