{
  "title": "Agl Method, Spel Class",
  "file": "vbg_Agl",
  "section": "Program",
  "type": "reference",
  "syntax": "Function Agl(JointNumber As Integer) As Single",
  "parameters": "JointNumber\tInteger expression from 1-9 representing the joint number.",
  "description": "Returns the joint angle for the selected rotational axis, or position for the selected linear axis.",
  "notes": "",
  "see_also": "Pls\n\nCX, CY, CZ, CU, CV, CW, CS, CT Keywords\n\nAgl Example\n\nVB Example:\n\nDim j1Angle As Single\n\nj1Angle = m_spel.Agl(1)\n\nC# Example:\n\nfloat j1Angle;\n\nj1Angle = m_spel.Agl(1);",
  "examples": [
    "Dim j1Angle As Single\nj1Angle = m_spel.Agl(1)",
    "float j1Angle;\nj1Angle = m_spel.Agl(1);"
  ]
}