{
  "title": "Vision Sequences",
  "file": "VisionSequences",
  "section": "Program",
  "type": "reference",
  "syntax": "",
  "parameters": "",
  "description": "Vision Sequences\n\nVision Sequences\n\nVision Sequences Overview\n\nVision Sequence Definition & General Information\n\nThe Vision Sequence Window\n\nVision Sequence Properties and Results\n\nCreating and Deleting Vision Sequences\n\nRunning Vision Sequences\n\nTesting and Debugging a Vision Sequence\n\nRunning Vision Sequences From SPEL\n\nImage Acquisition",
  "notes": "",
  "see_also": "",
  "examples": []
}