{
  "title": "Plist Command",
  "file": "cmd_plist",
  "section": "Operator",
  "type": "reference",
  "syntax": "(1) PList\n\n(2) PList\n\t\t\tpointNumber\n\n(3) PList\n\t\t\tstartPoint,\n\n(4) PList\n\t\t\tstartPoint,  endPoint",
  "parameters": "pointNumber\tThe number range is 0 to 999.\n\nStartPoint\tThe start point number. The number range is 0 to 999.\n\nEndPoint\tThe end point index. The number range is 0 to 999.",
  "description": "Plist displays point data in memory for the current robot.\n\nWhen there is no point data within the specified range of points, no data will be displayed.\n\nWhen a start point number is specified larger than the end point number, then an error occurs.\n\n(1) PList\n\nDisplays the coordinate data for all points.\n\n(2) PList pointIndex\n\nDisplays the coordinate data for the specified point.\n\n(3) PList startPoint,\n\nDisplays the coordinate data for all points starting with startPoint.\n\n(4) PList startPoint,  endPoint\n\nDisplays the coordinate data for all points starting with startPoint and ending with endPoint.\n\nPlist Example\n\nDisplay type depends on the robot type and existence of additional axes.\n\nThe following examples are for a Scara robot without additional axes.\n\nDisplays the specified point data:\n\n> plist 1\n\nP1   = XY(\n   200.000,\n    0.000,\n  -20.000,\n    0.000) /R /0\n\n>\n\nThis one displays the point data within the range of 10 and 20. In this example, only three points are found in this range.\n\n> plist 10, 20\n\nP10  = XY(\n   290.000,\n    0.000,\n  -20.000,\n    0.000) /R /0\n\nP12  = XY(\n   300.000,\n    0.000,\n    0.000,\n    0.000) /R /0\n\nP20  =\n   XY(285.000,\n   10.000,\n  -30.000,\n   45.000) /R /0\n\n>\n\nThis example displays the point data starting with point number 10.\n\n> plist 10,\n\nP10  =\n   XY(290.000,\n    0.000,\n  -20.000,\n    0.000) /R /0\n\nP12  =\n   XY(300.000,\n    0.000,\n    0.000,\n    0.000) /R /0\n\nP20  =\n   XY(285.000,\n   10.000,\n  -30.000,\n   45.000) /R /0\n\nP30  = XY(\n   310.000,\n   20.000,\n  -50.000,\n   90.000) /R /0",
  "notes": "",
  "see_also": "",
  "examples": [
    "> plist 1",
    "P1   = XY(\n   200.000,\n    0.000, -20.000,\n    0.000) /R /0",
    ">",
    "> plist 10, 20",
    "P10  = XY(\n   290.000,\n    0.000, -20.000,\n    0.000) /R /0",
    "P12  = XY(\n   300.000,\n    0.000,\n    0.000,\n    0.000) /R /0",
    "P20  =\n   XY(285.000,\n   10.000, -30.000,\n   45.000) /R /0",
    ">",
    "> plist 10,",
    "P10  =\n   XY(290.000,\n    0.000, -20.000,\n    0.000) /R /0",
    "P12  =\n   XY(300.000,\n    0.000,\n    0.000,\n    0.000) /R /0",
    "P20  =\n   XY(285.000,\n   10.000, -30.000,\n   45.000) /R /0",
    "P30  = XY(\n   310.000,\n   20.000, -50.000,\n   90.000) /R /0"
  ]
}