{
  "title": "StatusBar Properties",
  "file": "StatusBar_Properties",
  "section": "Program",
  "type": "reference",
  "syntax": "",
  "parameters": "",
  "description": "StatusBar Properties\n\nStatusBar Properties and Events\n\nThe following list is a summary of the StatusBar control properties with brief descriptions.  Click on the property names for more details.\n\nProperty\tDescription\n\nBackColor\tThe background color for the control.\n\nDefault: Control\n\nBorderStyle\tThe border used for the control.\n\nDefault: 0 - None\n\nDock\tSets docking position on the form for a control.\n\nDefault:2 -Bottom\n\nEnabled\tSets whether the control is enabled at runtime.\n\nDefault: 1 - True\n\nEventTaskType\tSets the type of task used for events.\n\nDefault: 0 - Normal\n\nFont\tThe font for the control text (design time only).\n\nDefault: Microsoft Sans Serif 8.25 pt\n\nForeColor\tThe foreground color for the control text.\n\nDefault: ControlText\n\nHeight\tThe height of the control in pixels.\n\nLeft\tThe left coordinate of the control in pixels.\n\nName\tThe name of the control.\n\nDefault: StatusBarXX\n\nRobotNumber\tSpecified the robot number used for ShowRobot.\n\nShowDateTime\tSets whether to display the current date and time.\n\nDefault: 0 - False\n\nShowEStop\tSets whether to display Estop status.\n\nDefault: 0 - False\n\nShowRobot\tSets whether to display the robot that is selected by the RobotNumber property.\n\nDefault: 0 - False\n\nShowSafeguard\tSets whether to display the Safeguard status.\n\nDefault: 0 - False\n\nTabIndex\tThe tab index of the control.\n\nText\tThe text displayed in the StatusBar text panel.\n\nDefault: Name of control\n\nToolTipText\tThe text used in the control's tooltip.\n\nDefault: Empty\n\nTop\tThe top coordinate of the control in pixels.\n\nVisible\tWhether the control is visible or not at runtime.\n\nDefault: 1 - True\n\nWidth\tSets the width of the Textbox control.\n\nDefault:\n\nEvent\tDescription\n\nClick\tExecutes when the user clicks the control with the mouse.",
  "notes": "",
  "see_also": "",
  "examples": []
}